reportabug/__init__.py
reportabug/__main__.py
reportabug-0.19.85.2.dist-info/LICENSE
reportabug-0.19.85.2.dist-info/METADATA
reportabug-0.19.85.2.dist-info/WHEEL
reportabug-0.19.85.2.dist-info/entry_points.txt
reportabug-0.19.85.2.dist-info/top_level.txt
reportabug-0.19.85.2.dist-info/zip-safe
reportabug-0.19.85.2.dist-info/RECORD
