Metadata-Version: 2.1
Name: reportabug
Version: 0.19.85.2
Summary: "A Python tool for collecting information when reporting bugs."
Home-page: https://github.com/zooba/reportabug
Author: Steve Dower
Author-email: steve.dower@python.org
License: UNKNOWN
Platform: UNKNOWN
Classifier: Development Status :: 3 - Alpha
Classifier: Intended Audience :: Developers
Classifier: License :: OSI Approved :: MIT License
Classifier: Operating System :: Microsoft :: Windows
Classifier: Programming Language :: Python :: 3.6
Classifier: Programming Language :: Python :: 3.7
Requires-Python: >=3.6
